cfn_clean/__init__.py
cfn_clean/yaml_dumper.py
cfn_flip/__init__.py
cfn_flip/__main__.py
cfn_flip/main.py
cfn_flip/yaml_dumper.py
cfn_tools/__init__.py
cfn_tools/json_encoder.py
cfn_tools/literal.py
cfn_tools/odict.py
cfn_tools/yaml_dumper.py
cfn_tools/yaml_loader.py
cfn_flip-1.2.2.dist-info/LICENSE
cfn_flip-1.2.2.dist-info/METADATA
cfn_flip-1.2.2.dist-info/NOTICE.txt
cfn_flip-1.2.2.dist-info/WHEEL
cfn_flip-1.2.2.dist-info/entry_points.txt
cfn_flip-1.2.2.dist-info/top_level.txt
cfn_flip-1.2.2.dist-info/RECORD
