Metadata-Version: 2.1
Name: cfn_flip
Version: 1.2.2
Summary: Convert AWS CloudFormation templates between JSON and YAML formats
Home-page: https://github.com/awslabs/aws-cfn-template-flip
Author: Steve Engledow
Author-email: sengledo@amazon.co.uk
License: Apache2
Platform: UNKNOWN
